Assignment_2.srcs/sources_1/new/pc.v
`timescale 1ns / 1ps
//////////////////////////////////////////////////////////////////////////////////
// Company: 
// Engineer: 
// 
// Create Date: 11/27/2024 03:09:11 AM
// Design Name: 
// Module Name: pc
// Project Name: 
// Target Devices: 
// Tool Versions: 
// Description: 
// 
// Dependencies: 
// 
// Revision:
// Revision 0.01 - File Created
// Additional Comments:
// 
//////////////////////////////////////////////////////////////////////////////////


module pc(
    input [31:0] next_val,
    input clk,
    output reg [31:0] current_val
    );

    initial begin
        current_val = 0;
    end
    
    always@(posedge clk) begin
        current_val <= next_val;
    end
    
endmodule

Assignment_2.srcs/sim_1/new/pc_tb.v
`timescale 1ns / 1ps
//////////////////////////////////////////////////////////////////////////////////
// Company: 
// Engineer: 
// 
// Create Date: 12/16/2024 01:56:38 AM
// Design Name: 
// Module Name: pc_tb
// Project Name: 
// Target Devices: 
// Tool Versions: 
// Description: 
// 
// Dependencies: 
// 
// Revision:
// Revision 0.01 - File Created
// Additional Comments:
// 
//////////////////////////////////////////////////////////////////////////////////

module pc_tb;

    // Inputs
    reg [31:0] next_val;
    reg clk;

    // Outputs
    wire [31:0] current_val;

    // Instantiate the Unit Under Test (UUT)
    pc uut (
        .next_val(next_val), 
        .clk(clk), 
        .current_val(current_val)
    );

    initial begin
        // Initialize Inputs
        next_val = 0;
        clk = 0;

        // Dump the VCD file
        $dumpfile("pc_tb.vcd");
        $dumpvars(0, pc_tb);

        // Wait 100 ns for global reset to finish
        #100;
        
        // Add stimulus here
        next_val = 32'hA5A5A5A5;
        #10;
        next_val = 32'h5A5A5A5A;
        #10;
        next_val = 32'hFFFFFFFF;
        #10;
        next_val = 32'h00000000;
        #10;

        // Finish simulation
        $finish;
    end
    
    always #5 clk = ~clk; // Clock generator

endmodule

Assignment_2.sim/sim_1/behav/xsim/pc_tb.vcd
$date
   Mon Dec 16 06:23:56 2024
$end
$version
  2019.1
$end
$timescale
  1ps
$end
$scope module pc_tb $end
$var reg 32 ! next_val [31:0] $end
$var reg 1 " clk $end
$var wire 32 # current_val [31:0] $end
$scope module uut $end
$var wire 32 $ next_val [31:0] $end
$var wire 1 % clk $end
$var reg 32 & current_val [31:0] $end
$upscope $end
$upscope $end
$enddefinitions $end
#0
$dumpvars
b0 !
0"
b0 #
b0 $
0%
b0 &
$end
#5000
1"
1%
b0 &
#10000
0"
0%
#15000
1"
1%
b0 &
#20000
0"
0%
#25000
1"
1%
b0 &
#30000
0"
0%
#35000
1"
1%
b0 &
#40000
0"
0%
#45000
1"
1%
b0 &
#50000
0"
0%
#55000
1"
1%
b0 &
#60000
0"
0%
#65000
1"
1%
b0 &
#70000
0"
0%
#75000
1"
1%
b0 &
#80000
0"
0%
#85000
1"
1%
b0 &
#90000
0"
0%
#95000
1"
1%
b0 &
#100000
b10100101101001011010010110100101 !
0"
b10100101101001011010010110100101 $
0%
#105000
1"
b10100101101001011010010110100101 #
1%
b10100101101001011010010110100101 &
#110000
b1011010010110100101101001011010 !
0"
b1011010010110100101101001011010 $
0%
#115000
1"
b1011010010110100101101001011010 #
1%
b1011010010110100101101001011010 &
#120000
b11111111111111111111111111111111 !
0"
b11111111111111111111111111111111 $
0%
#125000
1"
b11111111111111111111111111111111 #
1%
b11111111111111111111111111111111 &
#130000
b0 !
0"
b0 $
0%
#135000
1"
b0 #
1%
b0 &
